gdal2tiles/__init__.py
gdal2tiles/gdal2tiles.py
gdal2tiles/utils.py
gdal2tiles-0.1.6.dist-info/AUTHORS.rst
gdal2tiles-0.1.6.dist-info/LICENSE
gdal2tiles-0.1.6.dist-info/METADATA
gdal2tiles-0.1.6.dist-info/WHEEL
gdal2tiles-0.1.6.dist-info/top_level.txt
gdal2tiles-0.1.6.dist-info/RECORD
