Metadata-Version: 2.1
Name: gdal2tiles
Version: 0.1.6
Summary: A python library for generating map tiles based on gdal2tiles.py script.
Home-page: https://github.com/tehamalab/gdal2tiles
Author: Tehamalab
Author-email: developers@tehamalab.com
License: MIT license
Keywords: gdal2tiles
Platform: UNKNOWN
Classifier: Development Status :: 2 - Pre-Alpha
Classifier: Intended Audience :: Developers
Classifier: License :: OSI Approved :: MIT License
Classifier: Natural Language :: English
Classifier: Programming Language :: Python :: 2
Classifier: Programming Language :: Python :: 2.7
Classifier: Programming Language :: Python :: 3
Classifier: Programming Language :: Python :: 3.5
Classifier: Programming Language :: Python :: 3.6
Provides-Extra: billiard
Requires-Dist: billiard ; extra == 'billiard'
